credopay_paymentgateway/__init__.py
credopay_paymentgateway/config.py
credopay_paymentgateway/gateway.py
credopay_paymentgateway/resources/__init__.py
credopay_paymentgateway/resources/order.py
credopay_paymentgateway/resources/transaction.py
tests/__init__.py
tests/test_gateway.py
tests/test_order.py
tests/test_transaction.py
credopay_paymentgateway-0.1.dist-info/LICENSE
credopay_paymentgateway-0.1.dist-info/METADATA
credopay_paymentgateway-0.1.dist-info/WHEEL
credopay_paymentgateway-0.1.dist-info/top_level.txt
credopay_paymentgateway-0.1.dist-info/RECORD
