Metadata-Version: 2.1
Name: credopay-paymentgateway
Version: 0.1
Summary: A Python library for the CredoPay payment gateway.
Author: Credopay
Author-email: support@credopay.com
Keywords: credopay,paymentgateway
Classifier: Programming Language :: Python :: 3
Classifier: License :: OSI Approved :: MIT License
Classifier: Operating System :: OS Independent
Requires-Python: >=3.6
License-File: LICENSE
Requires-Dist: requests
